pytest_enhancements.py
pytest_enhancements-0.0.4.dist-info/LICENSE
pytest_enhancements-0.0.4.dist-info/METADATA
pytest_enhancements-0.0.4.dist-info/WHEEL
pytest_enhancements-0.0.4.dist-info/entry_points.txt
pytest_enhancements-0.0.4.dist-info/top_level.txt
pytest_enhancements-0.0.4.dist-info/RECORD
